JsonsPract/Jsons.py
JsonsPract/__init__.py
JsonsPract-0.0.4.dist-info/METADATA
JsonsPract-0.0.4.dist-info/WHEEL
JsonsPract-0.0.4.dist-info/top_level.txt
JsonsPract-0.0.4.dist-info/RECORD
