Metadata-Version: 2.1
Name: JsonsPract
Version: 0.0.4
Summary: This is the simplest module for quick work with json files.
Author: sonin
Author-email: fediasonin@gmail.com
Classifier: Programming Language :: Python :: 3.11
Classifier: License :: OSI Approved :: MIT License
Classifier: Operating System :: OS Independent
Requires-Python: >=3.6
Requires-Dist: requests >=2.25.1
